<?xml version="1.0" encoding="UTF-8"?>
<build-type xmlns:xsi="http://www.w3.org/2001/XMLSchema-instance" uuid="63debc19-5b9d-40be-a4d9-9a54c84b71e8" xsi:noNamespaceSchemaLocation="http://www.jetbrains.com/teamcity/schemas/9.0/project-config.xsd">
  <name>beta RELEASE</name>
  <description />
  <settings>
    <parameters />
    <build-runners>
      <runner id="RUNNER_2" name="" type="VS.Solution">
        <parameters>
          <param name="build-file-path" value="aimp_dotnet.sln" />
          <param name="msbuild.prop.Configuration" value="Release" />
          <param name="msbuild_version" value="12.0" />
          <param name="targets" value="Rebuild" />
          <param name="teamcity.step.mode" value="default" />
          <param name="toolsVersion" value="12.0" />
          <param name="vs.version" value="vs2013" />
        </parameters>
      </runner>
    </build-runners>
    <vcs-settings>
      <vcs-entry-ref root-id="AimpDotnet_GitRepo" />
    </vcs-settings>
    <requirements />
    <build-triggers />
    <cleanup />
  </settings>
</build-type>

